kontik1337.py
kontik1337-1.0.2.dist-info/METADATA
kontik1337-1.0.2.dist-info/WHEEL
kontik1337-1.0.2.dist-info/entry_points.txt
kontik1337-1.0.2.dist-info/top_level.txt
kontik1337-1.0.2.dist-info/RECORD
